{
    "/js/vendor.bundle.js": "/js/vendor.bundle.js",
    "/code~markdown~paragraph.bundle.js": "/code~markdown~paragraph.bundle.js",
    "/vendors~markdown~paragraph~stackedit-input.bundle.js": "/vendors~markdown~paragraph~stackedit-input.bundle.js",
    "/vendors~markdown~paragraph.bundle.js": "/vendors~markdown~paragraph.bundle.js",
    "/js/app.bundle.js": "/js/app.bundle.js",
    "/js/manifest.js": "/js/manifest.js",
    "/alert.bundle.js": "/alert.bundle.js",
    "/app-content.bundle.js": "/app-content.bundle.js",
    "/autocomplete.bundle.js": "/autocomplete.bundle.js",
    "/bitwise-flags.bundle.js": "/bitwise-flags.bundle.js",
    "/blockly.bundle.js": "/blockly.bundle.js",
    "/btn-gtroup.bundle.js": "/btn-gtroup.bundle.js",
    "/btn-list.bundle.js": "/btn-list.bundle.js",
    "/builder.bundle.js": "/builder.bundle.js",
    "/calendar.bundle.js": "/calendar.bundle.js",
    "/checkbox.bundle.js": "/checkbox.bundle.js",
    "/code.bundle.js": "/code.bundle.js",
    "/color.bundle.js": "/color.bundle.js",
    "/common.bundle.js": "/common.bundle.js",
    "/current-cart.bundle.js": "/current-cart.bundle.js",
    "/datetable.bundle.js": "/datetable.bundle.js",
    "/datetime.bundle.js": "/datetime.bundle.js",
    "/fields-renderer.bundle.js": "/fields-renderer.bundle.js",
    "/file-upload.bundle.js": "/file-upload.bundle.js",
    "/formjson.bundle.js": "/formjson.bundle.js",
    "/gorup-tabs.bundle.js": "/gorup-tabs.bundle.js",
    "/group-exp.bundle.js": "/group-exp.bundle.js",
    "/group-single-exp.bundle.js": "/group-single-exp.bundle.js",
    "/group-treeview.bundle.js": "/group-treeview.bundle.js",
    "/image-upload.bundle.js": "/image-upload.bundle.js",
    "/json-input.bundle.js": "/json-input.bundle.js",
    "/live-window.bundle.js": "/live-window.bundle.js",
    "/login-card.bundle.js": "/login-card.bundle.js",
    "/markdown.bundle.js": "/markdown.bundle.js",
    "/multi-upload.bundle.js": "/multi-upload.bundle.js",
    "/multitext.bundle.js": "/multitext.bundle.js",
    "/objects-list.bundle.js": "/objects-list.bundle.js",
    "/pagination.bundle.js": "/pagination.bundle.js",
    "/paragraph.bundle.js": "/paragraph.bundle.js",
    "/product-card.bundle.js": "/product-card.bundle.js",
    "/product-childrens-card.bundle.js": "/product-childrens-card.bundle.js",
    "/range.bundle.js": "/range.bundle.js",
    "/reports-chart.bundle.js": "/reports-chart.bundle.js",
    "/select.bundle.js": "/select.bundle.js",
    "/simple-captcha.bundle.js": "/simple-captcha.bundle.js",
    "/stackedit-input.bundle.js": "/stackedit-input.bundle.js",
    "/switch.bundle.js": "/switch.bundle.js",
    "/timer-card.bundle.js": "/timer-card.bundle.js",
    "/vendors~datetable.bundle.js": "/vendors~datetable.bundle.js",
    "/vendors~file-upload.bundle.js": "/vendors~file-upload.bundle.js",
    "/vendors~json-input.bundle.js": "/vendors~json-input.bundle.js",
    "/vendors~paragraph.bundle.js": "/vendors~paragraph.bundle.js",
    "/vendors~reports-chart.bundle.js": "/vendors~reports-chart.bundle.js",
    "/vendors~stackedit-input.bundle.js": "/vendors~stackedit-input.bundle.js",
    "/vendors~video-player.bundle.js": "/vendors~video-player.bundle.js",
    "/video-link.bundle.js": "/video-link.bundle.js",
    "/video-player.bundle.js": "/video-player.bundle.js"
}
